justic/__init__.py
justic/__main__.py
justic/core.py
justic/utils.py
justic-1.0.0.dist-info/METADATA
justic-1.0.0.dist-info/WHEEL
justic-1.0.0.dist-info/entry_points.txt
justic-1.0.0.dist-info/top_level.txt
justic-1.0.0.dist-info/RECORD
