Metadata-Version: 2.1
Name: justic
Version: 1.0.0
Summary: Just a static site generator
Home-page: https://github.com/axju/justic
Author: axju
Author-email: moin@axju.de
License: MIT
Platform: UNKNOWN
Classifier: Intended Audience :: Developers
Classifier: Operating System :: OS Independent
Classifier: Programming Language :: Python
Classifier: Programming Language :: Python :: 3.6
Classifier: Programming Language :: Python :: 3.7
Classifier: Programming Language :: Python :: 3.8
Classifier: Programming Language :: Python :: 3.9
Requires-Dist: jinja2
